<?xml version="1.0" encoding="iso-8859-1" standalone="yes"?>

<pattrstorage name = "ali.js-interp.xml">
	<slot number = "1">
		<pattr name = "ali-js-interp" value = "-0.4 0. 1 0.5 0.5 1 0 0 0.3 0.333 1. 0.5 0.5 0. 0. 1. -0.25 -0.65 0.32 0.1 1 0. 1. 0. 0.552645 -0.408477 1 0.5 0.5 0.329412 0.972549 1. 0.078091 -0.168196 0.362957 0.5 0.5 1. 0.109804 0.529412" />
	</slot>
	<slot number = "2">
		<pattr name = "ali-js-interp" value = "-0.605528 0.611554 0.685788 0.5 0.5 1 0 0 0.575403 -0.479 1. 0.5 0.5 0. 0. 1. -0.605528 -0.262094 0.499249 0.1623 0.284211 1. 0.988235 0.054902 0.647705 0.587453 1 0.5 0.5 0.447059 1. 0.560784 0.009038 0.611554 0.164729 0.5 0.5 0.984314 1. 0.329412 -0.141591 -0.86461 0.820752 0.658284 0.182417 1 0 0" />
	</slot>
	<slot number = "3">
		<pattr name = "ali-js-interp" value = "-0.237994 0.26812 0.685788 0.5 0.5 1 0 0 0.780258 -0.726032 1. 0.5 0.5 0. 0. 1. -0.563352 -0.780258 0.535098 1.945145 0.353139 1. 0.988235 0.054902 0.810384 0.29222 1 0.5 0.5 0.447059 1. 0.560784 0.003013 -0.599503 0.164729 0.5 0.5 0.984314 1. 0.329412" />
	</slot>
	<slot number = "4">
		<pattr name = "ali-js-interp" value = "0.10544 0.382598 1 0.14 0.14 1 0 0 0.485025 -0.521176 1 0.14 0.14 0.031373 0. 1." />
	</slot>
	<slot number = "5">
		<pattr name = "ali-js-interp" value = "0.10544 0.382598 3.456758 0.366666 0.072398 1 0 0 0.334396 -0.376572 1 0.337505 0.105536 0.031373 0. 1. 0.28017 -0.033138 0.967403 0.379688 0.998674 0. 1. 0. -0.521176 -0.075314 0.392664 0.154581 0.556218 0.976471 1. 0.109804" />
	</slot>
</pattrstorage>

